pygoodwe/__init__.py
pygoodwe/py.typed
pygoodwe-0.1.9.dist-info/LICENSE
pygoodwe-0.1.9.dist-info/METADATA
pygoodwe-0.1.9.dist-info/WHEEL
pygoodwe-0.1.9.dist-info/RECORD
