Metadata-Version: 2.3
Name: pygoodwe
Version: 0.1.9
Summary: A command line tool and python library to query the GOODWE SEMS Portal APIs.
License: MIT
Keywords: goodwe,solar,api,pygoodwe
Author: James Hodgkinson
Author-email: james@terminaloutcomes.com
Requires-Python: >=3.9,<4.0
Classifier: Development Status :: 4 - Beta
Classifier: License :: OSI Approved :: MIT License
Classifier: Operating System :: OS Independent
Classifier: Programming Language :: Python :: 3
Classifier: Programming Language :: Python :: 3.9
Classifier: Programming Language :: Python :: 3.10
Classifier: Programming Language :: Python :: 3.11
Classifier: Programming Language :: Python :: 3.12
Classifier: Programming Language :: Python :: 3.13
Requires-Dist: requests (>=2.28.1,<3.0.0)
Project-URL: bug tracker, https://github.com/yaleman/pygoodwe/issues
Project-URL: documentation, https://yaleman.github.io/pygoodwe/
Project-URL: homepage, https://github.com/yaleman/pygoodwe
Project-URL: repository, https://github.com/yaleman/pygoodwe
